pepsales_retry_lib/__init__.py
pepsales_retry_lib/kafka_consumer.py
pepsales_retry_lib/kafka_producer.py
pepsales_retry_lib-1.0.3.dist-info/licenses/LICENSE
pepsales_retry_lib-1.0.3.dist-info/METADATA
pepsales_retry_lib-1.0.3.dist-info/WHEEL
pepsales_retry_lib-1.0.3.dist-info/top_level.txt
pepsales_retry_lib-1.0.3.dist-info/RECORD
